litecrawl/__init__.py
litecrawl-0.7.8.dist-info/METADATA
litecrawl-0.7.8.dist-info/WHEEL
litecrawl-0.7.8.dist-info/RECORD
