Metadata-Version: 2.4
Name: litecrawl
Version: 0.7.8
Summary: Minimal asynchronous cron-friendly Playwright-based targeted web crawler.
Author: Jakob M. Wang
License: MIT
Requires-Python: >=3.12
Requires-Dist: aiosqlite>=0.20.0
Requires-Dist: filetype>=1.2.0
Requires-Dist: lxml>=5.1.0
Requires-Dist: playwright>=1.42.0
Provides-Extra: dev
Requires-Dist: pytest-asyncio>=0.23.0; extra == 'dev'
Requires-Dist: pytest>=8.3.0; extra == 'dev'
Requires-Dist: ruff>=0.7.0; extra == 'dev'
